__init__.py
skekchess/board.py
skekchess/chessman.py
skekchess/enums.py
skekchess/skek_chess.py
skekchess-0.0.2.dist-info/LICENSE
skekchess-0.0.2.dist-info/METADATA
skekchess-0.0.2.dist-info/WHEEL
skekchess-0.0.2.dist-info/top_level.txt
skekchess-0.0.2.dist-info/RECORD
