Metadata-Version: 2.1
Name: skekchess
Version: 0.0.2
Summary: Chess but for my own use.
Author-email: Skekdog <skekdog@gmail.com>
Classifier: Programming Language :: Python :: 3
Classifier: License :: OSI Approved :: MIT License
Classifier: Operating System :: OS Independent
Requires-Python: >=3.10
License-File: LICENSE
